jee_data_base/__init__.py
jee_data_base/cache/__init__.py
jee_data_base/core/__init__.py
jee_data_base/core/cache.py
jee_data_base/core/chapter.py
jee_data_base/core/data_base.py
jee_data_base/core/filter.py
jee_data_base/core/pdfy.py
jee_data_base/core/question.py
jee_data_base/core/styles.py
jee_data_base/core/utils.py
jee_data_base-0.1.0.dist-info/licenses/LICENSE
jee_data_base-0.1.0.dist-info/METADATA
jee_data_base-0.1.0.dist-info/WHEEL
jee_data_base-0.1.0.dist-info/top_level.txt
jee_data_base-0.1.0.dist-info/RECORD
