Metadata-Version: 2.4
Name: jee_data_base
Version: 0.1.0
Summary: JEE Mains PYQS data base
Home-page: https://github.com/HostServer001/jee_mains_pyqs_data_base
Author: HostServer001
Author-email: HostServer001 <jarvisuserbot@gmail.com>
License: MIT
Requires-Python: >=3.11
License-File: LICENSE
Requires-Dist: sentence_transformers
Requires-Dist: hdbscan
Requires-Dist: numpy
Requires-Dist: requests
Requires-Dist: tqdm
Dynamic: author
Dynamic: home-page
Dynamic: license-file
